bitcoin_dca/__init__.py
bitcoin_dca/_version.py
bitcoin_dca/backtester.py
bitcoin_dca/data_loader.py
bitcoin_dca/dca_analyzer.py
bitcoin_dca/main.py
bitcoin_dca/market_indicators.py
bitcoin_dca/predictor.py
bitcoin_dca-1.3.0.dist-info/licenses/LICENSE
bitcoin_dca-1.3.0.dist-info/METADATA
bitcoin_dca-1.3.0.dist-info/WHEEL
bitcoin_dca-1.3.0.dist-info/entry_points.txt
bitcoin_dca-1.3.0.dist-info/top_level.txt
bitcoin_dca-1.3.0.dist-info/RECORD
