Metadata-Version: 2.4
Name: bitcoin-dca
Version: 1.3.0
Summary: Advanced Bitcoin DCA analysis with machine learning predictions and strategy optimization
Author-email: Albert Garcia <obokaman@gmail.com>
License: MIT
Project-URL: Homepage, https://github.com/obokaman-com/bitcoin-dca
Project-URL: Bug Reports, https://github.com/obokaman-com/bitcoin-dca/issues
Project-URL: Source, https://github.com/obokaman-com/bitcoin-dca
Keywords: bitcoin,cryptocurrency,dca,dollar-cost-averaging,investment,analysis,machine-learning,prediction
Classifier: Development Status :: 4 - Beta
Classifier: Intended Audience :: Financial and Insurance Industry
Classifier: Intended Audience :: End Users/Desktop
Classifier: Operating System :: OS Independent
Classifier: Programming Language :: Python :: 3
Classifier: Programming Language :: Python :: 3.8
Classifier: Programming Language :: Python :: 3.9
Classifier: Programming Language :: Python :: 3.10
Classifier: Programming Language :: Python :: 3.11
Classifier: Programming Language :: Python :: 3.12
Classifier: Topic :: Office/Business :: Financial :: Investment
Classifier: Topic :: Scientific/Engineering :: Artificial Intelligence
Classifier: Environment :: Console
Requires-Python: >=3.8
License-File: LICENSE
Requires-Dist: pandas>=1.3.0
Requires-Dist: numpy>=1.21.0
Requires-Dist: scikit-learn>=1.0.0
Requires-Dist: tensorflow>=2.8.0
Requires-Dist: rich>=12.0.0
Requires-Dist: click>=8.0.0
Requires-Dist: ta<1.0.0,>=0.10.2
Requires-Dist: xgboost<2.1.0,>=1.7.0
Requires-Dist: requests>=2.25.0
Requires-Dist: packaging>=21.0
Requires-Dist: importlib-metadata>=1.0; python_version < "3.8"
Dynamic: license-file
